{
  "unversionedId": "reference/langref/relay_op",
  "id": "reference/langref/relay_op",
  "title": "Relay Core Tensor Operators",
  "description": "This page contains the list of core tensor operator primitives",
  "source": "@site/docs/reference/langref/relay_op.md",
  "sourceDirName": "reference/langref",
  "slug": "/reference/langref/relay_op",
  "permalink": "/docs/reference/langref/relay_op",
  "draft": false,
  "tags": [],
  "version": "current",
  "frontMatter": {
    "title": "Relay Core Tensor Operators"
  },
  "sidebar": "tutorialSidebar",
  "previous": {
    "title": "Expressions in Relay",
    "permalink": "/docs/reference/langref/relay_expr"
  },
  "next": {
    "title": "Pattern Matching in Relay",
    "permalink": "/docs/reference/langref/relay_pattern"
  }
}